{
  "$schema": "https://ornithemc.net/mc-versions/gen1/schemas/version.json",
  "client": true,
  "displayVersion": "1.18 Release Candidate 3",
  "downloads": {
    "client": {
      "sha1": "060dd014d59c90d723db87f9c9cedb511f374a71",
      "size": 20038747,
      "url": "https://launcher.mojang.com/v1/objects/060dd014d59c90d723db87f9c9cedb511f374a71/client.jar"
    },
    "client_mappings": {
      "sha1": "b64667a23e5ea5f0cc0547241c253d2a72a97c56",
      "size": 6610979,
      "url": "https://launcher.mojang.com/v1/objects/b64667a23e5ea5f0cc0547241c253d2a72a97c56/client.txt"
    },
    "server": {
      "sha1": "9a03d2c4ec2c737ce9d17a43d3774cdc0ea21030",
      "size": 46323763,
      "url": "https://launcher.mojang.com/v1/objects/9a03d2c4ec2c737ce9d17a43d3774cdc0ea21030/server.jar"
    },
    "server_mappings": {
      "sha1": "a36b4033a861c6e9bd3ced78b267e6aeaa75b639",
      "size": 5115917,
      "url": "https://launcher.mojang.com/v1/objects/a36b4033a861c6e9bd3ced78b267e6aeaa75b639/server.txt"
    }
  },
  "id": "1.18-rc3",
  "libraries": [
    "com.github.oshi:oshi-core:5.8.2",
    "com.google.code.gson:gson:2.8.8",
    "com.google.guava:failureaccess:1.0.1",
    "com.google.guava:guava:31.0.1-jre",
    "com.ibm.icu:icu4j:69.1",
    "com.mojang:authlib:3.2.38",
    "com.mojang:blocklist:1.0.6",
    "com.mojang:brigadier:1.0.18",
    "com.mojang:datafixerupper:4.0.26",
    "com.mojang:javabridge:1.2.24",
    "com.mojang:patchy:2.1.6",
    "com.mojang:text2speech:1.11.3",
    "commons-codec:commons-codec:1.15",
    "commons-io:commons-io:2.11.0",
    "commons-logging:commons-logging:1.2",
    "io.netty:netty-all:4.1.68.Final",
    "it.unimi.dsi:fastutil:8.5.6",
    "net.java.dev.jna:jna-platform:5.9.0",
    "net.java.dev.jna:jna:5.9.0",
    "net.sf.jopt-simple:jopt-simple:5.0.4",
    "org.apache.commons:commons-compress:1.21",
    "org.apache.commons:commons-lang3:3.12.0",
    "org.apache.httpcomponents:httpclient:4.5.13",
    "org.apache.httpcomponents:httpcore:4.4.14",
    "org.apache.logging.log4j:log4j-api:2.14.1",
    "org.apache.logging.log4j:log4j-core:2.14.1",
    "org.apache.logging.log4j:log4j-slf4j18-impl:2.14.1",
    "org.lwjgl:lwjgl-glfw:3.2.2",
    "org.lwjgl:lwjgl-jemalloc:3.2.2",
    "org.lwjgl:lwjgl-openal:3.2.2",
    "org.lwjgl:lwjgl-opengl:3.2.2",
    "org.lwjgl:lwjgl-stb:3.2.2",
    "org.lwjgl:lwjgl-tinyfd:3.2.2",
    "org.lwjgl:lwjgl:3.2.2",
    "org.slf4j:slf4j-api:1.8.0-beta4"
  ],
  "next": [
    "1.18-rc4"
  ],
  "normalizedVersion": "1.18.0-rc.3",
  "previous": [
    "1.18-rc2"
  ],
  "protocol": {
    "type": "netty-snapshot",
    "version": 59
  },
  "publicTime": "2021-11-26T16:09:00+00:00",
  "releaseTarget": "1.18",
  "releaseTime": "2021-11-26T15:51:56+00:00",
  "server": true,
  "sharedMappings": true,
  "world": {
    "format": "anvil",
    "version": 2858
  }
}